hytale_region_parser/__init__.py
hytale_region_parser/chunk_parser.py
hytale_region_parser/cli.py
hytale_region_parser/models.py
hytale_region_parser/py.typed
hytale_region_parser/region_parser.py
hytale_region_parser/storage.py
hytale_region_parser-0.1.2.dist-info/METADATA
hytale_region_parser-0.1.2.dist-info/WHEEL
hytale_region_parser-0.1.2.dist-info/entry_points.txt
hytale_region_parser-0.1.2.dist-info/licenses/LICENSE
hytale_region_parser-0.1.2.dist-info/RECORD
