Metadata-Version: 2.4
Name: hytale-region-parser
Version: 0.1.2
Summary: Parser for Hytale .region.bin files (IndexedStorageFile format)
Project-URL: Homepage, https://github.com/TheMcSebi/hytale-region-parser
Project-URL: Documentation, https://github.com/TheMcSebi/hytale-region-parser#readme
Project-URL: Repository, https://github.com/TheMcSebi/hytale-region-parser.git
Project-URL: Issues, https://github.com/TheMcSebi/hytale-region-parser/issues
Project-URL: Changelog, https://github.com/TheMcSebi/hytale-region-parser/blob/main/CHANGELOG.md
Author: Hytale Region Parser Contributors
License-Expression: MIT
License-File: LICENSE
Keywords: bson,game,hytale,modding,parser,region
Classifier: Development Status :: 4 - Beta
Classifier: Environment :: Console
Classifier: Intended Audience :: Developers
Classifier: License :: OSI Approved :: MIT License
Classifier: Operating System :: OS Independent
Classifier: Programming Language :: Python :: 3
Classifier: Programming Language :: Python :: 3.8
Classifier: Programming Language :: Python :: 3.9
Classifier: Programming Language :: Python :: 3.10
Classifier: Programming Language :: Python :: 3.11
Classifier: Programming Language :: Python :: 3.12
Classifier: Programming Language :: Python :: 3.13
Classifier: Topic :: Games/Entertainment
Classifier: Topic :: Software Development :: Libraries :: Python Modules
Classifier: Topic :: Utilities
Classifier: Typing :: Typed
Requires-Python: >=3.8
Requires-Dist: bson>=0.5.10
Requires-Dist: zstandard>=0.18.0
Provides-Extra: dev
Requires-Dist: mypy>=1.0.0; extra == 'dev'
Requires-Dist: pytest-cov>=4.0.0; extra == 'dev'
Requires-Dist: pytest>=7.0.0; extra == 'dev'
Requires-Dist: ruff>=0.1.0; extra == 'dev'
